{
  "project_info": {
    "project_number": "343410960080",
    "firebase_url": "https://a3csci3130-cc8eb.firebaseio.com",
    "project_id": "a3csci3130-cc8eb",
    "storage_bucket": "a3csci3130-cc8eb.appspot.com"
  },
  "client": [
    {
      "client_info": {
        "mobilesdk_app_id": "1:343410960080:android:6409f2945731fca6",
        "android_client_info": {
          "package_name": "com.acme.a3csci3130"
        }
      },
      "oauth_client": [
        {
          "client_id": "343410960080-btolvs7fggj6g9ua819fmk1qq1mcuhjf.apps.googleusercontent.com",
          "client_type": 3
        }
      ],
      "api_key": [
        {
          "current_key": "AIzaSyCQBSjhYZl3p5b71ezfNxn2iIrdChnc2Eo"
        }
      ],
      "services": {
        "analytics_service": {
          "status": 1
        },
        "appinvite_service": {
          "status": 1,
          "other_platform_oauth_client": []
        },
        "ads_service": {
          "status": 2
        }
      }
    }
  ],
  "configuration_version": "1"
}